{
	"001":{
		"sub":[{
				"subimg":"../img/wfgd01_180x180.png",
				"subject":"魅蓝 3S"
			},
			{
				"subimg":"../img/wfgd01_180x180.png",
				"subject":"魅蓝 3S"
			},
			{
				"subimg":"../img/wfgd01_180x180.png",
				"subject":"魅蓝 3S"
			}
		],
		"adrs":"../img/menu1.jpg"
	},
	
	"002":{
		"sub":[{
				"subimg":"../img/wfgd01_180x180.png",
				"subject":"魅蓝 3S"
			},
			{
				"subimg":"../img/wfgd01_180x180.png",
				"subject":"魅蓝 3S"
			},
			{
				"subimg":"../img/wfgd01_180x180.png",
				"subject":"魅蓝 3S"
			}
		],
		"adrs":"../img/menu1.jpg"
	}
	
}

